CHANGES.rst
CONTRIBUTORS.rst
MANIFEST.in
README.rst
setup.cfg
setup.py
docs/LICENSE.GPL
docs/LICENSE.rst
docs/index.rst
src/experimental/__init__.py
src/experimental.bwtools.egg-info/PKG-INFO
src/experimental.bwtools.egg-info/SOURCES.txt
src/experimental.bwtools.egg-info/dependency_links.txt
src/experimental.bwtools.egg-info/entry_points.txt
src/experimental.bwtools.egg-info/namespace_packages.txt
src/experimental.bwtools.egg-info/not-zip-safe
src/experimental.bwtools.egg-info/requires.txt
src/experimental.bwtools.egg-info/top_level.txt
src/experimental/bwtools/__init__.py
src/experimental/bwtools/configure.zcml
src/experimental/bwtools/interfaces.py
src/experimental/bwtools/setuphandlers.py
src/experimental/bwtools/testing.py
src/experimental/bwtools/browser/__init__.py
src/experimental/bwtools/browser/bwtools.py
src/experimental/bwtools/browser/configure.zcml
src/experimental/bwtools/browser/static/.gitkeep
src/experimental/bwtools/browser/static/scripts/check.js
src/experimental/bwtools/browser/static/scripts/worker.js
src/experimental/bwtools/browser/static/test/0.bz2
src/experimental/bwtools/browser/static/test/100K.bz2
src/experimental/bwtools/browser/templates/check.pt
src/experimental/bwtools/locales/experimental.bwtools.pot
src/experimental/bwtools/locales/update.sh
src/experimental/bwtools/profiles/default/browserlayer.xml
src/experimental/bwtools/profiles/default/metadata.xml
src/experimental/bwtools/profiles/default/registry.xml
src/experimental/bwtools/profiles/uninstall/browserlayer.xml
src/experimental/bwtools/profiles/uninstall/registry.xml
src/experimental/bwtools/tests/__init__.py
src/experimental/bwtools/tests/test_robot.py
src/experimental/bwtools/tests/test_setup.py
src/experimental/bwtools/tests/test_views.py
src/experimental/bwtools/tests/robot/test_example.robot
src/experimental/bwtools/upgrades/__init__.py
src/experimental/bwtools/upgrades/configure.zcml
src/experimental/bwtools/upgrades/profiles.zcml
src/experimental/bwtools/upgrades/to1001.py