Metadata-Version: 1.1
Name: experimental.bwtools
Version: 0.2.0
Summary: Experimental bandwidth tools
Home-page: https://pypi.python.org/pypi/experimental.bwtools
Author: Alessandro Pisa
Author-email: alessandro.pisa@gmail.com
License: GPL version 2
Keywords: Python Plone
Platform: UNKNOWN
Classifier: Environment :: Web Environment
Classifier: Framework :: Plone
Classifier: Framework :: Plone :: 5.0
Classifier: Framework :: Plone :: 5.1
Classifier: Programming Language :: Python
Classifier: Programming Language :: Python :: 2.7
Classifier: Operating System :: OS Independent
Classifier: License :: OSI Approved :: GNU General Public License v2 (GPLv2)
